kaisaglobalapi_test/__init__.py
kaisaglobalapi_test/readme.md
kaisaglobalapi_test/common/KaisaCrypto.py
kaisaglobalapi_test/common/KaisaFinaData.py
kaisaglobalapi_test/common/KaisaGateway.py
kaisaglobalapi_test/common/KaisaHistQuoteData.py
kaisaglobalapi_test/common/KaisaProtoc.py
kaisaglobalapi_test/common/KaisaTechData.py
kaisaglobalapi_test/common/__init__.py
kaisaglobalapi_test/common/com.py
kaisaglobalapi_test/common/pub_cls_com.py
kaisaglobalapi_test/common/utils.py
kaisaglobalapi_test/common/KCrypto/__init__.py
kaisaglobalapi_test/common/KCrypto/__init__.pyi
kaisaglobalapi_test/common/KCrypto/app.py
kaisaglobalapi_test/common/KCrypto/decryptoapp.py
kaisaglobalapi_test/common/KCrypto/pct_warnings.py
kaisaglobalapi_test/common/KCrypto/py.typed
kaisaglobalapi_test/common/KCrypto/settings.py
kaisaglobalapi_test/common/KCrypto/Cipher/AES.py
kaisaglobalapi_test/common/KCrypto/Cipher/AES.pyi
kaisaglobalapi_test/common/KCrypto/Cipher/ARC2.py
kaisaglobalapi_test/common/KCrypto/Cipher/ARC2.pyi
kaisaglobalapi_test/common/KCrypto/Cipher/ARC4.py
kaisaglobalapi_test/common/KCrypto/Cipher/ARC4.pyi
kaisaglobalapi_test/common/KCrypto/Cipher/Blowfish.py
kaisaglobalapi_test/common/KCrypto/Cipher/Blowfish.pyi
kaisaglobalapi_test/common/KCrypto/Cipher/CAST.py
kaisaglobalapi_test/common/KCrypto/Cipher/CAST.pyi
kaisaglobalapi_test/common/KCrypto/Cipher/ChaCha20.py
kaisaglobalapi_test/common/KCrypto/Cipher/ChaCha20.pyi
kaisaglobalapi_test/common/KCrypto/Cipher/ChaCha20_Poly1305.py
kaisaglobalapi_test/common/KCrypto/Cipher/ChaCha20_Poly1305.pyi
kaisaglobalapi_test/common/KCrypto/Cipher/DES.py
kaisaglobalapi_test/common/KCrypto/Cipher/DES.pyi
kaisaglobalapi_test/common/KCrypto/Cipher/DES3.py
kaisaglobalapi_test/common/KCrypto/Cipher/DES3.pyi
kaisaglobalapi_test/common/KCrypto/Cipher/PKCS1_OAEP.py
kaisaglobalapi_test/common/KCrypto/Cipher/PKCS1_OAEP.pyi
kaisaglobalapi_test/common/KCrypto/Cipher/PKCS1_v1_5.py
kaisaglobalapi_test/common/KCrypto/Cipher/PKCS1_v1_5.pyi
kaisaglobalapi_test-1.2.3.8.dist-info/METADATA
kaisaglobalapi_test-1.2.3.8.dist-info/WHEEL
kaisaglobalapi_test-1.2.3.8.dist-info/top_level.txt
kaisaglobalapi_test-1.2.3.8.dist-info/RECORD
