Metadata-Version: 2.1
Name: kaisaglobalapi-test
Version: 1.2.3.8
Summary: Kaisa Global Quantitative Trading API
Home-page: https://www.kaisaglobal.com/open-api
Author: KAISA FINANCIAL GROUP LTD.
Author-email: itsupport@kaisafin.com
License: Apache License 2.0
Keywords: Kaisa Global HK Stock Quant Trading API
Platform: UNKNOWN
Requires-Dist: requests (>=2.25.1)
Requires-Dist: urllib3 (>=1.25.8)
Requires-Dist: numpy (>=1.18.1)
Requires-Dist: pandas (>=1.1.3)
Requires-Dist: websocket-client (>=1.1.0)
Requires-Dist: json5 (>=0.9.1)
Requires-Dist: crypto (==1.4.1)
